modulation/__init__.py
modulation/classification/__init__.py
modulation/classification/procedure.py
modulation/classification/architecture/__init__.py
modulation/classification/architecture/cepstral_a.py
modulation/classification/architecture/m5.py
modulation/classification/metrics/__init__.py
modulation/classification/metrics/lwlrap.py
modulation/classification/seperation/__init__.py
modulation/classification/seperation/audio_unet.py
modulation/data/__init__.py
modulation/data/signal_generator.py
modulation/data/audio/__init__.py
modulation/data/audio/speech/__init__.py
modulation/data/audio/speech/recognition/__init__.py
modulation/data/audio/speech/recognition/common_voice.py
modulation/data/audio/speech/recognition/libri_speech.py
modulation/data/audio/speech/recognition/speech_command.py
modulation/data/audio/speech/recognition/vctk.py
modulation/data/audio/speech/recognition/yes_no.py
modulation/data/audio/speech/seperation/__init__.py
modulation/data/audio/speech/seperation/dsd100.py
modulation/entry_points/__init__.py
modulation/entry_points/cli.py
modulation/entry_points/tensorboard_entry_point.py
modulation/jax_utilities/__init__.py
modulation/jax_utilities/fourier.py
modulation/regression/__init__.py
modulation/regression/linear_predictive_coding.py
modulation/regression/spectral_denoise.py
modulation/regression/denoising/__init__.py
modulation/regression/denoising/band_pass.py
modulation/regression/denoising/finger_print.py
modulation/signal_utilities/__init__.py
modulation/signal_utilities/chopping.py
modulation/signal_utilities/segmentation.py
modulation/signal_utilities/splitting.py
modulation/signal_utilities/audio_utilities/__init__.py
modulation/signal_utilities/audio_utilities/filtering.py
modulation/signal_utilities/audio_utilities/persistence.py
modulation/signal_utilities/noise_generation/__init__.py
modulation/signal_utilities/noise_generation/additive_noise.py
modulation/signal_utilities/noise_generation/babble_noise.py
Modulation-0.0.4.dist-info/LICENSE.md
Modulation-0.0.4.dist-info/METADATA
Modulation-0.0.4.dist-info/WHEEL
Modulation-0.0.4.dist-info/entry_points.txt
Modulation-0.0.4.dist-info/top_level.txt
Modulation-0.0.4.dist-info/RECORD
